mainfile/__init__.py
mainfile/ashFile.py
ash_encrypt-0.2.0.dist-info/LICENSE
ash_encrypt-0.2.0.dist-info/METADATA
ash_encrypt-0.2.0.dist-info/WHEEL
ash_encrypt-0.2.0.dist-info/entry_points.txt
ash_encrypt-0.2.0.dist-info/top_level.txt
ash_encrypt-0.2.0.dist-info/RECORD
