Metadata-Version: 2.1
Name: ash-encrypt
Version: 0.2.0
Summary: Encrypt and Decrypt picture and file
Author: shimaf
Author-email: fshima02@gmail.com
License: UNKNOWN
Platform: UNKNOWN
Classifier: Programming Language :: Python :: 3
Classifier: License :: OSI Approved :: MIT License
Classifier: Operating System :: OS Independent
Requires-Python: >=3.6
License-File: LICENSE
